prompt_pipeline/__init__.py
prompt_pipeline/decorators.py
prompt_pipeline/pipeline.py
prompt_pipeline/prompt.py
prompt_pipeline/types.py
prompt_pipeline-0.1.1.dist-info/METADATA
prompt_pipeline-0.1.1.dist-info/WHEEL
prompt_pipeline-0.1.1.dist-info/licenses/LICENSE
prompt_pipeline-0.1.1.dist-info/RECORD
