Metadata-Version: 2.4
Name: prompt-pipeline
Version: 0.1.1
Summary: A Python package to simplify type-safe LLM prompts chaining
Project-URL: Homepage, https://github.com/zPy52/prompt-pipeline
Project-URL: Repository, https://github.com/zPy52/prompt-pipeline
Project-URL: Issues, https://github.com/zPy52/prompt-pipeline/issues
Author-email: Antonio Peña Peña <antoniopenapena52@gmail.com>
License:                                  Apache License
License-File: LICENSE
Classifier: Development Status :: 3 - Alpha
Classifier: Intended Audience :: Developers
Classifier: License :: OSI Approved :: Apache Software License
Classifier: Programming Language :: Python :: 3
Classifier: Programming Language :: Python :: 3.8
Classifier: Programming Language :: Python :: 3.9
Classifier: Programming Language :: Python :: 3.10
Classifier: Programming Language :: Python :: 3.11
Classifier: Programming Language :: Python :: 3.12
Requires-Python: >=3.8
Requires-Dist: openai>=1.66.3
Requires-Dist: pydantic>=2.10.6
